bhaptics_python-0.2.0.dist-info/METADATA
bhaptics_python-0.2.0.dist-info/WHEEL
bhaptics_python.libs/libcrypto-fca80f7e.so.3
bhaptics_python.libs/libssl-e50e007b.so.3
bhaptics_python/__init__.py
bhaptics_python/bhaptics_python.cpython-38-x86_64-linux-gnu.so
bhaptics_python-0.2.0.dist-info/RECORD
