Metadata-Version: 2.4
Name: bhaptics-python
Version: 0.2.0
Classifier: Development Status :: 4 - Beta
Classifier: Intended Audience :: Developers
Classifier: License :: OSI Approved :: MIT License
Classifier: Operating System :: OS Independent
Classifier: Programming Language :: Rust
Classifier: Programming Language :: Python :: Implementation :: CPython
Classifier: Programming Language :: Python :: 3
Classifier: Programming Language :: Python :: 3.8
Classifier: Programming Language :: Python :: 3.9
Classifier: Programming Language :: Python :: 3.10
Classifier: Programming Language :: Python :: 3.11
Classifier: Programming Language :: Python :: 3.12
Summary: bHaptics Python Library
Keywords: haptics,bhaptics
License: MIT
Requires-Python: >=3.8
Project-URL: Repository, https://github.com/bhaptics/tact-python
Project-URL: Homepage, https://github.com/bhaptics/tact-python
